LICENSE
synbconvert/__init__.py
synbconvert/cli.py
synbconvert/python_file_handler.py
synbconvert/syn_notebook_handler.py
synbconvert/synbconvert.py
synbconvert/utils.py
synbconvert-0.7.0.dist-info/entry_points.txt
synbconvert-0.7.0.dist-info/LICENSE
synbconvert-0.7.0.dist-info/WHEEL
synbconvert-0.7.0.dist-info/METADATA
synbconvert-0.7.0.dist-info/RECORD
