Metadata-Version: 2.1
Name: synbconvert
Version: 0.7.0
Summary: A simple command line tool to convert Python files to Synapse Notebooks and vice versa.
Home-page: https://github.com/alpine-data/synbconvert
License: MIT
Keywords: python,converter,notebook,azure,synapse-analytics
Author: Jan Bieser
Author-email: janwithb@gmail.com
Requires-Python: >=3.9,<4.0
Classifier: License :: OSI Approved :: MIT License
Classifier: Programming Language :: Python :: 3
Classifier: Programming Language :: Python :: 3.9
Classifier: Programming Language :: Python :: 3.10
Requires-Dist: click (>=8.0.4,<9.0.0)
Project-URL: Documentation, https://alpine-data.github.io/synbconvert/
Project-URL: Repository, https://github.com/alpine-data/synbconvert
